LICENSE
MANIFEST.in
setup.py
docspad/__init__.py
docspad/docspad.py
docspad_sdk.egg-info/PKG-INFO
docspad_sdk.egg-info/SOURCES.txt
docspad_sdk.egg-info/dependency_links.txt
docspad_sdk.egg-info/top_level.txt