Metadata-Version: 1.1
Name: docspad-sdk
Version: 0.5
Summary: Docspad SDK
Home-page: https://github.com/bookpad/docspad-sdk-python
Author: Rajat Khanduja
Author-email: rajatkhanduja13@gmail.com
License: UNKNOWN
Platform: UNKNOWN
Classifier: Programming Language :: Python
Classifier: Programming Language :: Python :: 2
Classifier: License :: OSI Approved :: MIT License
Classifier: Operating System :: OS Independent
Classifier: Development Status :: 2 - Pre-Alpha
Classifier: Intended Audience :: Developers
Classifier: Topic :: Software Development :: Libraries
